verimoog_1_7/verimoog_1_7.srcs/sources_1/imports/new/saw_wav_gen.v
`timescale 1ns / 1ps
//////////////////////////////////////////////////////////////////////////////////
// Company: San Diego State University
// Engineer: 
//
// Create Date: 09/26/2024
// Design Name: Sawtooth Wave Generator
// Module Name: saw_wav_gen
// Project Name: VeriMoog Synthesizer
// Target Devices: Generic FPGA
// Tool Versions:
// Description:
//    Phase accumulator-based sawtooth wave generator with configurable frequency.
//    Produces an 8-bit output with linear ramp from 0 to 255.
//
// Key Features:
//    - Variable frequency generation (0-20kHz range)
//    - 8-bit amplitude resolution
//    - Phase-accurate synthesis
//    - Glitch-free frequency changes
//
// Signal Information:
//    Inputs:
//        clk       - 100MHz system clock
//        reset     - Active high reset
//        freq      - 32-bit frequency control word (Hz)
//    Outputs:
//        wav_out   - 8-bit sawtooth wave output
//
// Timing:
//    - Output updates every clock cycle
//    - Phase accumulator overflow determines frequency
//    - 32-bit phase resolution for fine frequency control
//
// Implementation Notes:
//    - Uses fixed-point arithmetic for phase calculation
//    - Direct phase accumulator to output mapping
//    - Phase increment calculation: (freq * 2^32) / clock_freq
//
// Performance:
//    - Frequency Resolution: 0.023 Hz at 100MHz clock
//    - Maximum Frequency: Limited by Nyquist (50MHz)
//    - Actual Usable Range: 0-20kHz for audio
//
// Dependencies: None
//
// Revision History:
// Revision 0.01 - Initial design
// Additional Comments:
//    - Consider adding frequency limit checking
//    - Could implement anti-aliasing filtering
//////////////////////////////////////////////////////////////////////////////////

module saw_wav_gen (
    input wire clk,
    input wire reset,
    input wire [31:0] freq,
    output reg [7:0] wav_out
);
    reg [31:0] phase_accumulator;
    reg [31:0] phase_increment;

    // Calculate phase increment using 64-bit arithmetic
    wire [63:0] phase_inc_calc;
    assign phase_inc_calc = ((freq * 64'h100000000) / 100_000_000);

    always @(posedge clk) begin
        if (reset) begin
            phase_accumulator <= 0;
            phase_increment <= 0;
            wav_out <= 0;
        end else begin
            // Update phase increment (registered to prevent glitches)
            phase_increment <= phase_inc_calc[31:0];

            // Update phase accumulator
            phase_accumulator <= phase_accumulator + phase_increment;

            // Use upper 8 bits of phase accumulator for output
            wav_out <= phase_accumulator[31:24];
        end
    end

endmodule

verimoog_1_7/verimoog_1_7.srcs/sim_1/imports/new/saw_wav_gen_tb.v
timescale 1ns / 1ps
//////////////////////////////////////////////////////////////////////////////////
// Company: 
// Engineer: 
// 
// Create Date: 09/27/2024 11:46:18 AM
// Design Name: 
// Module Name: saw_wav_gen_tb
// Project Name: 
// Target Devices: 
// Tool Versions: 
// Description: 
//   Testbench for sine wave generator.
// 
// Dependencies: 
// 
// Revision:
// Revision 0.01 - File created
// Additional Comments:
// 
//////////////////////////////////////////////////////////////////////////////////

module saw_wav_gen_tb;
    // Test bench signals
    reg clk;
    reg reset;
    reg [31:0] freq;
    wire [7:0] wav_out;

    // Instantiate sawtooth wave generator
    saw_wav_gen uut (
        .clk(clk),
        .reset(reset),
        .freq(freq),
        .wav_out(wav_out)
    );

    // Clock generation
    initial begin
        clk = 0;
        forever #5 clk = ~clk; // 100MHz clock
    end

    // Test stimulus
    initial begin
        // Initialize waveform dumps
        $dumpfile("saw_wav_gen_tb.vcd");
        $dumpvars(0, saw_wav_gen_tb);
        
        // Initialize signals
        reset = 1;
        freq = 0;
        
        // Release reset
        #100;
        reset = 0;
        #100;

        // Test different frequencies
        // Test Middle C (261.63 Hz)
        $display("Testing Middle C (261.63 Hz)...");
        freq = 32'd262;
        #10000;

        // Test A4 (440 Hz)
        $display("Testing A4 (440 Hz)...");
        freq = 32'd440;
        #10000;

        // Test E4 (329.63 Hz)
        $display("Testing E4 (329.63 Hz)...");
        freq = 32'd330;
        #10000;

        // Test reset during operation
        $display("Testing reset behavior...");
        reset = 1;
        #100;
        reset = 0;
        #100;

        // Test frequency change during operation
        $display("Testing frequency change...");
        freq = 32'd523; // C5
        #10000;

        $display("Simulation complete");
        $finish;
    end

    // Monitor changes
    initial begin
        $monitor("Time=%0t freq=%0d wav_out=%h", $time, freq, wav_out);
    end

endmodule

saw_wav_gen_tb.vcd
$date
	Mon Dec  2 21:29:04 2024
$end
$version
	Icarus Verilog
$end
$timescale
	1ps
$end
$scope module saw_wav_gen_tb $end
$var wire 8 ! wav_out [7:0] $end
$var reg 1 " clk $end
$var reg 32 # freq [31:0] $end
$var reg 1 $ reset $end
$scope module uut $end
$var wire 1 " clk $end
$var wire 32 % freq [31:0] $end
$var wire 1 $ reset $end
$var wire 64 & phase_inc_calc [63:0] $end
$var reg 32 ' phase_accumulator [31:0] $end
$var reg 32 ( phase_increment [31:0] $end
$var reg 8 ) wav_out [7:0] $end
$upscope $end
$upscope $end
$enddefinitions $end
$comment Show the parameter values. $end
$dumpall
$end
#0
$dumpvars
bx )
bx (
bx '
b0 &
b0 %
1$
b0 #
0"
bx !
$end
#5000
b0 !
b0 )
b0 (
b0 '
1"
#10000
0"
#15000
1"
#20000
0"
#25000
1"
#30000
0"
#35000
1"
#40000
0"
#45000
1"
#50000
0"
#55000
1"
#60000
0"
#65000
1"
#70000
0"
#75000
1"
#80000
0"
#85000
1"
#90000
0"
#95000
1"
#100000
0"
0$
#105000
1"
#110000
0"
#115000
1"
#120000
0"
#125000
1"
#130000
0"
#135000
1"
#140000
0"
#145000
1"
#150000
0"
#155000
1"
#160000
0"
#165000
1"
#170000
0"
#175000
1"
#180000
0"
#185000
1"
#190000
0"
#195000
1"
#200000
0"
b10101111110100 &
b100000110 #
b100000110 %
#205000
b10101111110100 (
1"
#210000
0"
#215000
b10101111110100 '
1"
#220000
0"
#225000
b101011111101000 '
1"
#230000
0"
#235000
b1000001111011100 '
1"
#240000
0"
#245000
b1010111111010000 '
1"
#250000
0"
#255000
b1101101111000100 '
1"
#260000
0"
#265000
b10000011110111000 '
1"
#270000
0"
#275000
b10011001110101100 '
1"
#280000
0"
#285000
b10101111110100000 '
1"
#290000
0"
#295000
b11000101110010100 '
1"
#300000
0"
#305000
b11011011110001000 '
1"
#310000
0"
#315000
b11110001101111100 '
1"
#320000
0"
#325000
b100000111101110000 '
1"
#330000
0"
#335000
b100011101101100100 '
1"
#340000
0"
#345000
b100110011101011000 '
1"
#350000
0"
#355000
b101001001101001100 '
1"
#360000
0"
#365000
b101011111101000000 '
1"
#370000
0"
#375000
b101110101100110100 '
1"
#380000
0"
#385000
b110001011100101000 '
1"
#390000
0"
#395000
b110100001100011100 '
1"
#400000
0"
#405000
b110110111100010000 '
1"
#410000
0"
#415000
b111001101100000100 '
1"
#420000
0"
#425000
b111100011011111000 '
1"
#430000
0"
#435000
b111111001011101100 '
1"
#440000
0"
#445000
b1000001111011100000 '
1"
#450000
0"
#455000
b1000100101011010100 '
1"
#460000
0"
#465000
b1000111011011001000 '
1"
#470000
0"
#475000
b1001010001010111100 '
1"
#480000
0"
#485000
b1001100111010110000 '
1"
#490000
0"
#495000
b1001111101010100100 '
1"
#500000
0"
#505000
b1010010011010011000 '
1"
#510000
0"
#515000
b1010101001010001100 '
1"
#520000
0"
#525000
b1010111111010000000 '
1"
#530000
0"
#535000
b1011010101001110100 '
1"
#540000
0"
#545000
b1011101011001101000 '
1"
#550000
0"
#555000
b1100000001001011100 '
1"
#560000
0"
#565000
b1100010111001010000 '
1"
#570000
0"
#575000
b1100101101001000100 '
1"
#580000
0"
#585000
b1101000011000111000 '
1"
#590000
0"
#595000
b1101011001000101100 '
1"
#600000
0"
#605000
b1101101111000100000 '
1"
#610000
0"
#615000
b1110000101000010100 '
1"
#620000
0"
#625000
b1110011011000001000 '
1"
#630000
0"
#635000
b1110110000111111100 '
1"
#640000
0"
#645000
b1111000110111110000 '
1"
#650000
0"
#655000
b1111011100111100100 '
1"
#660000
0"
#665000
b1111110010111011000 '
1"
#670000
0"
#675000
b10000001000111001100 '
1"
#680000
0"
#685000
b10000011110111000000 '
1"
#690000
0"
#695000
b10000110100110110100 '
1"
#700000
0"
#705000
b10001001010110101000 '
1"
#710000
0"
#715000
b10001100000110011100 '
1"
#720000
0"
#725000
b10001110110110010000 '
1"
#730000
0"
#735000
b10010001100110000100 '
1"
#740000
0"
#745000
b10010100010101111000 '
1"
#750000
0"
#755000
b10010111000101101100 '
1"
#760000
0"
#765000
b10011001110101100000 '
1"
#770000
0"
#775000
b10011100100101010100 '
1"
#780000
0"
#785000
b10011111010101001000 '
1"
#790000
0"
#795000
b10100010000100111100 '
1"
#800000
0"
#805000
b10100100110100110000 '
1"
#810000
0"
#815000
b10100111100100100100 '
1"
#820000
0"
#825000
b10101010010100011000 '
1"
#830000
0"
#835000
b10101101000100001100 '
1"
#840000
0"
#845000
b10101111110100000000 '
1"
#850000
0"
#855000
b10110010100011110100 '
1"
#860000
0"
#865000
b10110101010011101000 '
1"
#870000
0"
#875000
b10111000000011011100 '
1"
#880000
0"
#885000
b10111010110011010000 '
1"
#890000
0"
#895000
b10111101100011000100 '
1"
#900000
0"
#905000
b11000000010010111000 '
1"
#910000
0"
#915000
b11000011000010101100 '
1"
#920000
0"
#925000
b11000101110010100000 '
1"
#930000
0"
#935000
b11001000100010010100 '
1"
#940000
0"
#945000
b11001011010010001000 '
1"
#950000
0"
#955000
b11001110000001111100 '
1"
#960000
0"
#965000
b11010000110001110000 '
1"
#970000
0"
#975000
b11010011100001100100 '
1"
#980000
0"
#985000
b11010110010001011000 '
1"
#990000
0"
#995000
b11011001000001001100 '
1"
#1000000
0"
#1005000
b11011011110001000000 '
1"
#1010000
0"
#1015000
b11011110100000110100 '
1"
#1020000
0"
#1025000
b11100001010000101000 '
1"
#1030000
0"
#1035000
b11100100000000011100 '
1"
#1040000
0"
#1045000
b11100110110000010000 '
1"
#1050000
0"
#1055000
b11101001100000000100 '
1"
#1060000
0"
#1065000
b11101100001111111000 '
1"
#1070000
0"
#1075000
b11101110111111101100 '
1"
#1080000
0"
#1085000
b11110001101111100000 '
1"
#1090000
0"
#1095000
b11110100011111010100 '
1"
#1100000
0"
#1105000
b11110111001111001000 '
1"
#1110000
0"
#1115000
b11111001111110111100 '
1"
#1120000
0"
#1125000
b11111100101110110000 '
1"
#1130000
0"
#1135000
b11111111011110100100 '
1"
#1140000
0"
#1145000
b100000010001110011000 '
1"
#1150000
0"
#1155000
b100000100111110001100 '
1"
#1160000
0"
#1165000
b100000111101110000000 '
1"
#1170000
0"
#1175000
b100001010011101110100 '
1"
#1180000
0"
#1185000
b100001101001101101000 '
1"
#1190000
0"
#1195000
b100001111111101011100 '
1"
#1200000
0"
#1205000
b100010010101101010000 '
1"
#1210000
0"
#1215000
b100010101011101000100 '
1"
#1220000
0"
#1225000
b100011000001100111000 '
1"
#1230000
0"
#1235000
b100011010111100101100 '
1"
#1240000
0"
#1245000
b100011101101100100000 '
1"
#1250000
0"
#1255000
b100100000011100010100 '
1"
#1260000
0"
#1265000
b100100011001100001000 '
1"
#1270000
0"
#1275000
b100100101111011111100 '
1"
#1280000
0"
#1285000
b100101000101011110000 '
1"
#1290000
0"
#1295000
b100101011011011100100 '
1"
#1300000
0"
#1305000
b100101110001011011000 '
1"
#1310000
0"
#1315000
b100110000111011001100 '
1"
#1320000
0"
#1325000
b100110011101011000000 '
1"
#1330000
0"
#1335000
b100110110011010110100 '
1"
#1340000
0"
#1345000
b100111001001010101000 '
1"
#1350000
0"
#1355000
b100111011111010011100 '
1"
#1360000
0"
#1365000
b100111110101010010000 '
1"
#1370000
0"
#1375000
b101000001011010000100 '
1"
#1380000
0"
#1385000
b101000100001001111000 '
1"
#1390000
0"
#1395000
b101000110111001101100 '
1"
#1400000
0"
#1405000
b101001001101001100000 '
1"
#1410000
0"
#1415000
b101001100011001010100 '
1"
#1420000
0"
#1425000
b101001111001001001000 '
1"
#1430000
0"
#1435000
b101010001111000111100 '
1"
#1440000
0"
#1445000
b101010100101000110000 '
1"
#1450000
0"
#1455000
b101010111011000100100 '
1"
#1460000
0"
#1465000
b101011010001000011000 '
1"
#1470000
0"
#1475000
b101011100111000001100 '
1"
#1480000
0"
#1485000
b101011111101000000000 '
1"
#1490000
0"
#1495000
b101100010010111110100 '
1"
#1500000
0"
#1505000
b101100101000111101000 '
1"
#1510000
0"
#1515000
b101100111110111011100 '
1"
#1520000
0"
#1525000
b101101010100111010000 '
1"
#1530000
0"
#1535000
b101101101010111000100 '
1"
#1540000
0"
#1545000
b101110000000110111000 '
1"
#1550000
0"
#1555000
b101110010110110101100 '
1"
#1560000
0"
#1565000
b101110101100110100000 '
1"
#1570000
0"
#1575000
b101111000010110010100 '
1"
#1580000
0"
#1585000
b101111011000110001000 '
1"
#1590000
0"
#1595000
b101111101110101111100 '
1"
#1600000
0"
#1605000
b110000000100101110000 '
1"
#1610000
0"
#1615000
b110000011010101100100 '
1"
#1620000
0"
#1625000
b110000110000101011000 '
1"
#1630000
0"
#1635000
b110001000110101001100 '
1"
#1640000
0"
#1645000
b110001011100101000000 '
1"
#1650000
0"
#1655000
b110001110010100110100 '
1"
#1660000
0"
#1665000
b110010001000100101000 '
1"
#1670000
0"
#1675000
b110010011110100011100 '
1"
#1680000
0"
#1685000
b110010110100100010000 '
1"
#1690000
0"
#1695000
b110011001010100000100 '
1"
#1700000
0"
#1705000
b110011100000011111000 '
1"
#1710000
0"
#1715000
b110011110110011101100 '
1"
#1720000
0"
#1725000
b110100001100011100000 '
1"
#1730000
0"
#1735000
b110100100010011010100 '
1"
#1740000
0"
#1745000
b110100111000011001000 '
1"
#1750000
0"
#1755000
b110101001110010111100 '
1"
#1760000
0"
#1765000
b110101100100010110000 '
1"
#1770000
0"
#1775000
b110101111010010100100 '
1"
#1780000
0"
#1785000
b110110010000010011000 '
1"
#1790000
0"
#1795000
b110110100110010001100 '
1"
#1800000
0"
#1805000
b110110111100010000000 '
1"
#1810000
0"
#1815000
b110111010010001110100 '
1"
#1820000
0"
#1825000
b110111101000001101000 '
1"
#1830000
0"
#1835000
b110111111110001011100 '
1"
#1840000
0"
#1845000
b111000010100001010000 '
1"
#1850000
0"
#1855000
b111000101010001000100 '
1"
#1860000
0"
#1865000
b111001000000000111000 '
1"
#1870000
0"
#1875000
b111001010110000101100 '
1"
#1880000
0"
#1885000
b111001101100000100000 '
1"
#1890000
0"
#1895000
b111010000010000010100 '
1"
#1900000
0"
#1905000
b111010011000000001000 '
1"
#1910000
0"
#1915000
b111010101101111111100 '
1"
#1920000
0"
#1925000
b111011000011111110000 '
1"
#1930000
0"
#1935000
b111011011001111100100 '
1"
#1940000
0"
#1945000
b111011101111111011000 '
1"
#1950000
0"
#1955000
b111100000101111001100 '
1"
#1960000
0"
#1965000
b111100011011111000000 '
1"
#1970000
0"
#1975000
b111100110001110110100 '
1"
#1980000
0"
#1985000
b111101000111110101000 '
1"
#1990000
0"
#1995000
b111101011101110011100 '
1"
#2000000
0"
#2005000
b111101110011110010000 '
1"
#2010000
0"
#2015000
b111110001001110000100 '
1"
#2020000
0"
#2025000
b111110011111101111000 '
1"
#2030000
0"
#2035000
b111110110101101101100 '
1"
#2040000
0"
#2045000
b111111001011101100000 '
1"
#2050000
0"
#2055000
b111111100001101010100 '
1"
#2060000
0"
#2065000
b111111110111101001000 '
1"
#2070000
0"
#2075000
b1000000001101100111100 '
1"
#2080000
0"
#2085000
b1000000100011100110000 '
1"
#2090000
0"
#2095000
b1000000111001100100100 '
1"
#2100000
0"
#2105000
b1000001001111100011000 '
1"
#2110000
0"
#2115000
b1000001100101100001100 '
1"
#2120000
0"
#2125000
b1000001111011100000000 '
1"
#2130000
0"
#2135000
b1000010010001011110100 '
1"
#2140000
0"
#2145000
b1000010100111011101000 '
1"
#2150000
0"
#2155000
b1000010111101011011100 '
1"
#2160000
0"
#2165000
b1000011010011011010000 '
1"
#2170000
0"
#2175000
b1000011101001011000100 '
1"
#2180000
0"
#2185000
b1000011111111010111000 '
1"
#2190000
0"
#2195000
b1000100010101010101100 '
1"
#2200000
0"
#2205000
b1000100101011010100000 '
1"
#2210000
0"
#2215000
b1000101000001010010100 '
1"
#2220000
0"
#2225000
b1000101010111010001000 '
1"
#2230000
0"
#2235000
b1000101101101001111100 '
1"
#2240000
0"
#2245000
b1000110000011001110000 '
1"
#2250000
0"
#2255000
b1000110011001001100100 '
1"
#2260000
0"
#2265000
b1000110101111001011000 '
1"
#2270000
0"
#2275000
b1000111000101001001100 '
1"
#2280000
0"
#2285000
b1000111011011001000000 '
1"
#2290000
0"
#2295000
b1000111110001000110100 '
1"
#2300000
0"
#2305000
b1001000000111000101000 '
1"
#2310000
0"
#2315000
b1001000011101000011100 '
1"
#2320000
0"
#2325000
b1001000110011000010000 '
1"
#2330000
0"
#2335000
b1001001001001000000100 '
1"
#2340000
0"
#2345000
b1001001011110111111000 '
1"
#2350000
0"
#2355000
b1001001110100111101100 '
1"
#2360000
0"
#2365000
b1001010001010111100000 '
1"
#2370000
0"
#2375000
b1001010100000111010100 '
1"
#2380000
0"
#2385000
b1001010110110111001000 '
1"
#2390000
0"
#2395000
b1001011001100110111100 '
1"
#2400000
0"
#2405000
b1001011100010110110000 '
1"
#2410000
0"
#2415000
b1001011111000110100100 '
1"
#2420000
0"
#2425000
b1001100001110110011000 '
1"
#2430000
0"
#2435000
b1001100100100110001100 '
1"
#2440000
0"
#2445000
b1001100111010110000000 '
1"
#2450000
0"
#2455000
b1001101010000101110100 '
1"
#2460000
0"
#2465000
b1001101100110101101000 '
1"
#2470000
0"
#2475000
b1001101111100101011100 '
1"
#2480000
0"
#2485000
b1001110010010101010000 '
1"
#2490000
0"
#2495000
b1001110101000101000100 '
1"
#2500000
0"
#2505000
b1001110111110100111000 '
1"
#2510000
0"
#2515000
b1001111010100100101100 '
1"
#2520000
0"
#2525000
b1001111101010100100000 '
1"
#2530000
0"
#2535000
b1010000000000100010100 '
1"
#2540000
0"
#2545000
b1010000010110100001000 '
1"
#2550000
0"
#2555000
b1010000101100011111100 '
1"
#2560000
0"
#2565000
b1010001000010011110000 '
1"
#2570000
0"
#2575000
b1010001011000011100100 '
1"
#2580000
0"
#2585000
b1010001101110011011000 '
1"
#2590000
0"
#2595000
b1010010000100011001100 '
1"
#2600000
0"
#2605000
b1010010011010011000000 '
1"
#2610000
0"
#2615000
b1010010110000010110100 '
1"
#2620000
0"
#2625000
b1010011000110010101000 '
1"
#2630000
0"
#2635000
b1010011011100010011100 '
1"
#2640000
0"
#2645000
b1010011110010010010000 '
1"
#2650000
0"
#2655000
b1010100001000010000100 '
1"
#2660000
0"
#2665000
b1010100011110001111000 '
1"
#2670000
0"
#2675000
b1010100110100001101100 '
1"
#2680000
0"
#2685000
b1010101001010001100000 '
1"
#2690000
0"
#2695000
b1010101100000001010100 '
1"
#2700000
0"
#2705000
b1010101110110001001000 '
1"
#2710000
0"
#2715000
b1010110001100000111100 '
1"
#2720000
0"
#2725000
b1010110100010000110000 '
1"
#2730000
0"
#2735000
b1010110111000000100100 '
1"
#2740000
0"
#2745000
b1010111001110000011000 '
1"
#2750000
0"
#2755000
b1010111100100000001100 '
1"
#2760000
0"
#2765000
b1010111111010000000000 '
1"
#2770000
0"
#2775000
b1011000001111111110100 '
1"
#2780000
0"
#2785000
b1011000100101111101000 '
1"
#2790000
0"
#2795000
b1011000111011111011100 '
1"
#2800000
0"
#2805000
b1011001010001111010000 '
1"
#2810000
0"
#2815000
b1011001100111111000100 '
1"
#2820000
0"
#2825000
b1011001111101110111000 '
1"
#2830000
0"
#2835000
b1011010010011110101100 '
1"
#2840000
0"
#2845000
b1011010101001110100000 '
1"
#2850000
0"
#2855000
b1011010111111110010100 '
1"
#2860000
0"
#2865000
b1011011010101110001000 '
1"
#2870000
0"
#2875000
b1011011101011101111100 '
1"
#2880000
0"
#2885000
b1011100000001101110000 '
1"
#2890000
0"
#2895000
b1011100010111101100100 '
1"
#2900000
0"
#2905000
b1011100101101101011000 '
1"
#2910000
0"
#2915000
b1011101000011101001100 '
1"
#2920000
0"
#2925000
b1011101011001101000000 '
1"
#2930000
0"
#2935000
b1011101101111100110100 '
1"
#2940000
0"
#2945000
b1011110000101100101000 '
1"
#2950000
0"
#2955000
b1011110011011100011100 '
1"
#2960000
0"
#2965000
b1011110110001100010000 '
1"
#2970000
0"
#2975000
b1011111000111100000100 '
1"
#2980000
0"
#2985000
b1011111011101011111000 '
1"
#2990000
0"
#2995000
b1011111110011011101100 '
1"
#3000000
0"
#3005000
b1100000001001011100000 '
1"
#3010000
0"
#3015000
b1100000011111011010100 '
1"
#3020000
0"
#3025000
b1100000110101011001000 '
1"
#3030000
0"
#3035000
b1100001001011010111100 '
1"
#3040000
0"
#3045000
b1100001100001010110000 '
1"
#3050000
0"
#3055000
b1100001110111010100100 '
1"
#3060000
0"
#3065000
b1100010001101010011000 '
1"
#3070000
0"
#3075000
b1100010100011010001100 '
1"
#3080000
0"
#3085000
b1100010111001010000000 '
1"
#3090000
0"
#3095000
b1100011001111001110100 '
1"
#3100000
0"
#3105000
b1100011100101001101000 '
1"
#3110000
0"
#3115000
b1100011111011001011100 '
1"
#3120000
0"
#3125000
b1100100010001001010000 '
1"
#3130000
0"
#3135000
b1100100100111001000100 '
1"
#3140000
0"
#3145000
b1100100111101000111000 '
1"
#3150000
0"
#3155000
b1100101010011000101100 '
1"
#3160000
0"
#3165000
b1100101101001000100000 '
1"
#3170000
0"
#3175000
b1100101111111000010100 '
1"
#3180000
0"
#3185000
b1100110010101000001000 '
1"
#3190000
0"
#3195000
b1100110101010111111100 '
1"
#3200000
0"
#3205000
b1100111000000111110000 '
1"
#3210000
0"
#3215000
b1100111010110111100100 '
1"
#3220000
0"
#3225000
b1100111101100111011000 '
1"
#3230000
0"
#3235000
b1101000000010111001100 '
1"
#3240000
0"
#3245000
b1101000011000111000000 '
1"
#3250000
0"
#3255000
b1101000101110110110100 '
1"
#3260000
0"
#3265000
b1101001000100110101000 '
1"
#3270000
0"
#3275000
b1101001011010110011100 '
1"
#3280000
0"
#3285000
b1101001110000110010000 '
1"
#3290000
0"
#3295000
b1101010000110110000100 '
1"
#3300000
0"
#3305000
b1101010011100101111000 '
1"
#3310000
0"
#3315000
b1101010110010101101100 '
1"
#3320000
0"
#3325000
b1101011001000101100000 '
1"
#3330000
0"
#3335000
b1101011011110101010100 '
1"
#3340000
0"
#3345000
b1101011110100101001000 '
1"
#3350000
0"
#3355000
b1101100001010100111100 '
1"
#3360000
0"
#3365000
b1101100100000100110000 '
1"
#3370000
0"
#3375000
b1101100110110100100100 '
1"
#3380000
0"
#3385000
b1101101001100100011000 '
1"
#3390000
0"
#3395000
b1101101100010100001100 '
1"
#3400000
0"
#3405000
b1101101111000100000000 '
1"
#3410000
0"
#3415000
b1101110001110011110100 '
1"
#3420000
0"
#3425000
b1101110100100011101000 '
1"
#3430000
0"
#3435000
b1101110111010011011100 '
1"
#3440000
0"
#3445000
b1101111010000011010000 '
1"
#3450000
0"
#3455000
b1101111100110011000100 '
1"
#3460000
0"
#3465000
b1101111111100010111000 '
1"
#3470000
0"
#3475000
b1110000010010010101100 '
1"
#3480000
0"
#3485000
b1110000101000010100000 '
1"
#3490000
0"
#3495000
b1110000111110010010100 '
1"
#3500000
0"
#3505000
b1110001010100010001000 '
1"
#3510000
0"
#3515000
b1110001101010001111100 '
1"
#3520000
0"
#3525000
b1110010000000001110000 '
1"
#3530000
0"
#3535000
b1110010010110001100100 '
1"
#3540000
0"
#3545000
b1110010101100001011000 '
1"
#3550000
0"
#3555000
b1110011000010001001100 '
1"
#3560000
0"
#3565000
b1110011011000001000000 '
1"
#3570000
0"
#3575000
b1110011101110000110100 '
1"
#3580000
0"
#3585000
b1110100000100000101000 '
1"
#3590000
0"
#3595000
b1110100011010000011100 '
1"
#3600000
0"
#3605000
b1110100110000000010000 '
1"
#3610000
0"
#3615000
b1110101000110000000100 '
1"
#3620000
0"
#3625000
b1110101011011111111000 '
1"
#3630000
0"
#3635000
b1110101110001111101100 '
1"
#3640000
0"
#3645000
b1110110000111111100000 '
1"
#3650000
0"
#3655000
b1110110011101111010100 '
1"
#3660000
0"
#3665000
b1110110110011111001000 '
1"
#3670000
0"
#3675000
b1110111001001110111100 '
1"
#3680000
0"
#3685000
b1110111011111110110000 '
1"
#3690000
0"
#3695000
b1110111110101110100100 '
1"
#3700000
0"
#3705000
b1111000001011110011000 '
1"
#3710000
0"
#3715000
b1111000100001110001100 '
1"
#3720000
0"
#3725000
b1111000110111110000000 '
1"
#3730000
0"
#3735000
b1111001001101101110100 '
1"
#3740000
0"
#3745000
b1111001100011101101000 '
1"
#3750000
0"
#3755000
b1111001111001101011100 '
1"
#3760000
0"
#3765000
b1111010001111101010000 '
1"
#3770000
0"
#3775000
b1111010100101101000100 '
1"
#3780000
0"
#3785000
b1111010111011100111000 '
1"
#3790000
0"
#3795000
b1111011010001100101100 '
1"
#3800000
0"
#3805000
b1111011100111100100000 '
1"
#3810000
0"
#3815000
b1111011111101100010100 '
1"
#3820000
0"
#3825000
b1111100010011100001000 '
1"
#3830000
0"
#3835000
b1111100101001011111100 '
1"
#3840000
0"
#3845000
b1111100111111011110000 '
1"
#3850000
0"
#3855000
b1111101010101011100100 '
1"
#3860000
0"
#3865000
b1111101101011011011000 '
1"
#3870000
0"
#3875000
b1111110000001011001100 '
1"
#3880000
0"
#3885000
b1111110010111011000000 '
1"
#3890000
0"
#3895000
b1111110101101010110100 '
1"
#3900000
0"
#3905000
b1111111000011010101000 '
1"
#3910000
0"
#3915000
b1111111011001010011100 '
1"
#3920000
0"
#3925000
b1111111101111010010000 '
1"
#3930000
0"
#3935000
b10000000000101010000100 '
1"
#3940000
0"
#3945000
b10000000011011001111000 '
1"
#3950000
0"
#3955000
b10000000110001001101100 '
1"
#3960000
0"
#3965000
b10000001000111001100000 '
1"
#3970000
0"
#3975000
b10000001011101001010100 '
1"
#3980000
0"
#3985000
b10000001110011001001000 '
1"
#3990000
0"
#3995000
b10000010001001000111100 '
1"
#4000000
0"
#4005000
b10000010011111000110000 '
1"
#4010000
0"
#4015000
b10000010110101000100100 '
1"
#4020000
0"
#4025000
b10000011001011000011000 '
1"
#4030000
0"
#4035000
b10000011100001000001100 '
1"
#4040000
0"
#4045000
b10000011110111000000000 '
1"
#4050000
0"
#4055000
b10000100001100111110100 '
1"
#4060000
0"
#4065000
b10000100100010111101000 '
1"
#4070000
0"
#4075000
b10000100111000111011100 '
1"
#4080000
0"
#4085000
b10000101001110111010000 '
1"
#4090000
0"
#4095000
b10000101100100111000100 '
1"
#4100000
0"
#4105000
b10000101111010110111000 '
1"
#4110000
0"
#4115000
b10000110010000110101100 '
1"
#4120000
0"
#4125000
b10000110100110110100000 '
1"
#4130000
0"
#4135000
b10000110111100110010100 '
1"
#4140000
0"
#4145000
b10000111010010110001000 '
1"
#4150000
0"
#4155000
b10000111101000101111100 '
1"
#4160000
0"
#4165000
b10000111111110101110000 '
1"
#4170000
0"
#4175000
b10001000010100101100100 '
1"
#4180000
0"
#4185000
b10001000101010101011000 '
1"
#4190000
0"
#4195000
b10001001000000101001100 '
1"
#4200000
0"
#4205000
b10001001010110101000000 '
1"
#4210000
0"
#4215000
b10001001101100100110100 '
1"
#4220000
0"
#4225000
b10001010000010100101000 '
1"
#4230000
0"
#4235000
b10001010011000100011100 '
1"
#4240000
0"
#4245000
b10001010101110100010000 '
1"
#4250000
0"
#4255000
b10001011000100100000100 '
1"
#4260000
0"
#4265000
b10001011011010011111000 '
1"
#4270000
0"
#4275000
b10001011110000011101100 '
1"
#4280000
0"
#4285000
b10001100000110011100000 '
1"
#4290000
0"
#4295000
b10001100011100011010100 '
1"
#4300000
0"
#4305000
b10001100110010011001000 '
1"
#4310000
0"
#4315000
b10001101001000010111100 '
1"
#4320000
0"
#4325000
b10001101011110010110000 '
1"
#4330000
0"
#4335000
b10001101110100010100100 '
1"
#4340000
0"
#4345000
b10001110001010010011000 '
1"
#4350000
0"
#4355000
b10001110100000010001100 '
1"
#4360000
0"
#4365000
b10001110110110010000000 '
1"
#4370000
0"
#4375000
b10001111001100001110100 '
1"
#4380000
0"
#4385000
b10001111100010001101000 '
1"
#4390000
0"
#4395000
b10001111111000001011100 '
1"
#4400000
0"
#4405000
b10010000001110001010000 '
1"
#4410000
0"
#4415000
b10010000100100001000100 '
1"
#4420000
0"
#4425000
b10010000111010000111000 '
1"
#4430000
0"
#4435000
b10010001010000000101100 '
1"
#4440000
0"
#4445000
b10010001100110000100000 '
1"
#4450000
0"
#4455000
b10010001111100000010100 '
1"
#4460000
0"
#4465000
b10010010010010000001000 '
1"
#4470000
0"
#4475000
b10010010100111111111100 '
1"
#4480000
0"
#4485000
b10010010111101111110000 '
1"
#4490000
0"
#4495000
b10010011010011111100100 '
1"
#4500000
0"
#4505000
b10010011101001111011000 '
1"
#4510000
0"
#4515000
b10010011111111111001100 '
1"
#4520000
0"
#4525000
b10010100010101111000000 '
1"
#4530000
0"
#4535000
b10010100101011110110100 '
1"
#4540000
0"
#4545000
b10010101000001110101000 '
1"
#4550000
0"
#4555000
b10010101010111110011100 '
1"
#4560000
0"
#4565000
b10010101101101110010000 '
1"
#4570000
0"
#4575000
b10010110000011110000100 '
1"
#4580000
0"
#4585000
b10010110011001101111000 '
1"
#4590000
0"
#4595000
b10010110101111101101100 '
1"
#4600000
0"
#4605000
b10010111000101101100000 '
1"
#4610000
0"
#4615000
b10010111011011101010100 '
1"
#4620000
0"
#4625000
b10010111110001101001000 '
1"
#4630000
0"
#4635000
b10011000000111100111100 '
1"
#4640000
0"
#4645000
b10011000011101100110000 '
1"
#4650000
0"
#4655000
b10011000110011100100100 '
1"
#4660000
0"
#4665000
b10011001001001100011000 '
1"
#4670000
0"
#4675000
b10011001011111100001100 '
1"
#4680000
0"
#4685000
b10011001110101100000000 '
1"
#4690000
0"
#4695000
b10011010001011011110100 '
1"
#4700000
0"
