verimoog_1_7/verimoog_1_7.srcs/sources_1/imports/new/sin_wav_gen.v
`timescale 1ns / 1ps
//////////////////////////////////////////////////////////////////////////////////
// Company: San Diego State University
// Engineer:
//
// Create Date: 09/27/2024
// Design Name: Sine Wave Generator
// Module Name: sin_wav_gen
// Project Name: VeriMoog Synthesizer
// Target Devices: Generic FPGA
// Tool Versions:
// Description:
//    Look-up table based sine wave generator with phase accumulator.
//    Produces band-limited sine waves with minimal harmonic distortion.
//
// Key Features:
//    - 256-point sine look-up table
//    - Phase-accurate frequency synthesis
//    - 8-bit amplitude resolution
//    - Continuous phase operation
//
// Signal Information:
//    Inputs:
//        clk       - 100MHz system clock
//        reset     - Active high reset
//        freq      - 32-bit frequency control word (Hz)
//    Outputs:
//        wav_out   - 8-bit sine wave output
//
// Implementation Details:
//    - Look-up table initialization uses $sin function
//    - Fixed-point phase accumulation
//    - Table size: 256 entries
//    - Output range: 0 to 255 (centered at 128)
//
// Mathematical Basis:
//    - Phase Increment = (freq * 2^32) / clock_freq
//    - Table Index = phase_accumulator[31:24]
//    - Sine Scaling = sin(2? * index / 256) * 127 + 128
//
// Performance:
//    - THD: < 0.5% (theoretical)
//    - Frequency Resolution: 0.023 Hz
//    - Amplitude Resolution: 8 bits
//
// Dependencies: None
//
// Revision History:
// Revision 0.01 - Initial design
// Additional Comments:
//    - Could implement linear interpolation
//    - Consider larger table for better resolution
//    - Possible cubic interpolation enhancement
//////////////////////////////////////////////////////////////////////////////////

module sin_wav_gen (
    input wire clk,
    input wire reset,
    input wire [31:0] freq,
    output reg [7:0] wav_out
);
    reg [31:0] phase_accumulator;
    reg [31:0] phase_increment;
    parameter integer TABLE_SIZE = 256;
    reg [7:0] sine_table [0:TABLE_SIZE-1];

    // Calculate phase increment based on 100 MHz clock
    // phase_increment = (freq * 2^32) / clock_frequency
    // This gives us proper frequency scaling with 32-bit fixed-point math
    wire [63:0] phase_inc_calc;
    assign phase_inc_calc = ((freq * 64'd4294967296) / 100_000_000);

    // Initialize sine wave lookup table
    integer i;
    initial begin
        for (i = 0; i < TABLE_SIZE; i = i + 1) begin
            // Generate sine values between 0 and 255
            sine_table[i] = $rtoi($sin(2.0 * 3.14159 * i / TABLE_SIZE) * 127.0 + 128.0);
        end
    end

    always @(posedge clk or posedge reset) begin
        if (reset) begin
            phase_accumulator <= 0;
            phase_increment <= 0;
            wav_out <= 8'h80; // Middle value (128)
        end else begin
            // Update phase increment
            phase_increment <= phase_inc_calc[31:0];

            // Update phase accumulator
            phase_accumulator <= phase_accumulator + phase_increment;

            // Use the top 8 bits of the phase accumulator to index into the sine table
            wav_out <= sine_table[phase_accumulator[31:24]];
        end
    end

    // Synthesis translate_off
    // Debug logic to verify frequency
    real current_freq;
    always @(phase_increment) begin
        current_freq = (phase_increment * 100_000_000.0) / 4294967296.0;
        $display("Requested Freq: %0d Hz, Actual Freq: %0f Hz", freq, current_freq);
    end
    // Synthesis translate_on

endmodule

verimoog_1_7/verimoog_1_7.srcs/sim_1/imports/new/sin_wav_gen_tb.v
`timescale 1ns / 1ps
//////////////////////////////////////////////////////////////////////////////////
// Company: 
// Engineer: 
// 
// Create Date: 09/27/2024 11:46:18 AM
// Design Name: 
// Module Name: sin_wav_gen_tb
// Project Name: 
// Target Devices: 
// Tool Versions: 
// Description: 
//   Testbench for sine wave generator.
// 
// Dependencies: 
// 
// Revision:
// Revision 0.01 - File created
// Additional Comments:
// 
//////////////////////////////////////////////////////////////////////////////////

module sin_wav_gen_tb;
    // Test bench signals
    reg clk;
    reg reset;
    reg [31:0] freq;
    wire [7:0] wav_out;

    // Instantiate sine wave generator
    sin_wav_gen uut (
        .clk(clk),
        .reset(reset),
        .freq(freq),
        .wav_out(wav_out)
    );

    // Clock generation
    initial begin
        clk = 0;
        forever #5 clk = ~clk; // 100MHz clock
    end

    // Test stimulus
    initial begin
        // Initialize waveform dumps
        $dumpfile("sin_wav_gen_tb.vcd");
        $dumpvars(0, sin_wav_gen_tb);
        
        // Initialize signals
        reset = 1;
        freq = 0;
        
        // Release reset
        #100;
        reset = 0;
        #100;

        // Test different frequencies
        // Test A4 (440 Hz)
        $display("Testing A4 (440 Hz)...");
        freq = 32'd440;
        #10000;

        // Test A3 (220 Hz)
        $display("Testing A3 (220 Hz)...");
        freq = 32'd220;
        #10000;

        // Test A5 (880 Hz)
        $display("Testing A5 (880 Hz)...");
        freq = 32'd880;
        #10000;

        // Test reset during operation
        $display("Testing reset behavior...");
        reset = 1;
        #100;
        reset = 0;
        #100;

        // Test very low frequency
        $display("Testing low frequency (110 Hz)...");
        freq = 32'd110;
        #10000;

        $display("Simulation complete");
        $finish;
    end

    // Monitor output for analysis
    initial begin
        $monitor("Time=%0t freq=%0d wav_out=%h", $time, freq, wav_out);
    end

endmodule

sin_wav_gen_tb.vcd
$date
	Mon Dec  2 21:18:34 2024
$end
$version
	Icarus Verilog
$end
$timescale
	1ps
$end
$scope module sin_wav_gen_tb $end
$var wire 8 ! wav_out [7:0] $end
$var reg 1 " clk $end
$var reg 32 # freq [31:0] $end
$var reg 1 $ reset $end
$scope module uut $end
$var wire 1 " clk $end
$var wire 32 % freq [31:0] $end
$var wire 1 $ reset $end
$var wire 64 & phase_inc_calc [63:0] $end
$var parameter 32 ' TABLE_SIZE $end
$var reg 32 ( phase_accumulator [31:0] $end
$var reg 32 ) phase_increment [31:0] $end
$var reg 8 * wav_out [7:0] $end
$var real 1 + current_freq $end
$var integer 32 , i [31:0] $end
$upscope $end
$upscope $end
$enddefinitions $end
$comment Show the parameter values. $end
$dumpall
b100000000 '
$end
#0
$dumpvars
b100000000 ,
r0 +
b10000000 *
b0 )
b0 (
b0 &
b0 %
1$
b0 #
0"
b10000000 !
$end
#5000
1"
#10000
0"
#15000
1"
#20000
0"
#25000
1"
#30000
0"
#35000
1"
#40000
0"
#45000
1"
#50000
0"
#55000
1"
#60000
0"
#65000
1"
#70000
0"
#75000
1"
#80000
0"
#85000
1"
#90000
0"
#95000
1"
#100000
0"
0$
#105000
1"
#110000
0"
#115000
1"
#120000
0"
#125000
1"
#130000
0"
#135000
1"
#140000
0"
#145000
1"
#150000
0"
#155000
1"
#160000
0"
#165000
1"
#170000
0"
#175000
1"
#180000
0"
#185000
1"
#190000
0"
#195000
1"
#200000
0"
b100100111010001 &
b110111000 #
b110111000 %
#205000
r439.9800673127174 +
b100100111010001 )
1"
#210000
0"
#215000
b100100111010001 (
1"
#220000
0"
#225000
b1001001110100010 (
1"
#230000
0"
#235000
b1101110101110011 (
1"
#240000
0"
#245000
b10010011101000100 (
1"
#250000
0"
#255000
b10111000100010101 (
1"
#260000
0"
#265000
b11011101011100110 (
1"
#270000
0"
#275000
b100000010010110111 (
1"
#280000
0"
#285000
b100100111010001000 (
1"
#290000
0"
#295000
b101001100001011001 (
1"
#300000
0"
#305000
b101110001000101010 (
1"
#310000
0"
#315000
b110010101111111011 (
1"
#320000
0"
#325000
b110111010111001100 (
1"
#330000
0"
#335000
b111011111110011101 (
1"
#340000
0"
#345000
b1000000100101101110 (
1"
#350000
0"
#355000
b1000101001100111111 (
1"
#360000
0"
#365000
b1001001110100010000 (
1"
#370000
0"
#375000
b1001110011011100001 (
1"
#380000
0"
#385000
b1010011000010110010 (
1"
#390000
0"
#395000
b1010111101010000011 (
1"
#400000
0"
#405000
b1011100010001010100 (
1"
#410000
0"
#415000
b1100000111000100101 (
1"
#420000
0"
#425000
b1100101011111110110 (
1"
#430000
0"
#435000
b1101010000111000111 (
1"
#440000
0"
#445000
b1101110101110011000 (
1"
#450000
0"
#455000
b1110011010101101001 (
1"
#460000
0"
#465000
b1110111111100111010 (
1"
#470000
0"
#475000
b1111100100100001011 (
1"
#480000
0"
#485000
b10000001001011011100 (
1"
#490000
0"
#495000
b10000101110010101101 (
1"
#500000
0"
#505000
b10001010011001111110 (
1"
#510000
0"
#515000
b10001111000001001111 (
1"
#520000
0"
#525000
b10010011101000100000 (
1"
#530000
0"
#535000
b10011000001111110001 (
1"
#540000
0"
#545000
b10011100110111000010 (
1"
#550000
0"
#555000
b10100001011110010011 (
1"
#560000
0"
#565000
b10100110000101100100 (
1"
#570000
0"
#575000
b10101010101100110101 (
1"
#580000
0"
#585000
b10101111010100000110 (
1"
#590000
0"
#595000
b10110011111011010111 (
1"
#600000
0"
#605000
b10111000100010101000 (
1"
#610000
0"
#615000
b10111101001001111001 (
1"
#620000
0"
#625000
b11000001110001001010 (
1"
#630000
0"
#635000
b11000110011000011011 (
1"
#640000
0"
#645000
b11001010111111101100 (
1"
#650000
0"
#655000
b11001111100110111101 (
1"
#660000
0"
#665000
b11010100001110001110 (
1"
#670000
0"
#675000
b11011000110101011111 (
1"
#680000
0"
#685000
b11011101011100110000 (
1"
#690000
0"
#695000
b11100010000100000001 (
1"
#700000
0"
#705000
b11100110101011010010 (
1"
#710000
0"
#715000
b11101011010010100011 (
1"
#720000
0"
#725000
b11101111111001110100 (
1"
#730000
0"
#735000
b11110100100001000101 (
1"
#740000
0"
#745000
b11111001001000010110 (
1"
#750000
0"
#755000
b11111101101111100111 (
1"
#760000
0"
#765000
b100000010010110111000 (
1"
#770000
0"
#775000
b100000110111110001001 (
1"
#780000
0"
#785000
b100001011100101011010 (
1"
#790000
0"
#795000
b100010000001100101011 (
1"
#800000
0"
#805000
b100010100110011111100 (
1"
#810000
0"
#815000
b100011001011011001101 (
1"
#820000
0"
#825000
b100011110000010011110 (
1"
#830000
0"
#835000
b100100010101001101111 (
1"
#840000
0"
#845000
b100100111010001000000 (
1"
#850000
0"
#855000
b100101011111000010001 (
1"
#860000
0"
#865000
b100110000011111100010 (
1"
#870000
0"
#875000
b100110101000110110011 (
1"
#880000
0"
#885000
b100111001101110000100 (
1"
#890000
0"
#895000
b100111110010101010101 (
1"
#900000
0"
#905000
b101000010111100100110 (
1"
#910000
0"
#915000
b101000111100011110111 (
1"
#920000
0"
#925000
b101001100001011001000 (
1"
#930000
0"
#935000
b101010000110010011001 (
1"
#940000
0"
#945000
b101010101011001101010 (
1"
#950000
0"
#955000
b101011010000000111011 (
1"
#960000
0"
#965000
b101011110101000001100 (
1"
#970000
0"
#975000
b101100011001111011101 (
1"
#980000
0"
#985000
b101100111110110101110 (
1"
#990000
0"
#995000
b101101100011101111111 (
1"
#1000000
0"
#1005000
b101110001000101010000 (
1"
#1010000
0"
#1015000
b101110101101100100001 (
1"
#1020000
0"
#1025000
b101111010010011110010 (
1"
#1030000
0"
#1035000
b101111110111011000011 (
1"
#1040000
0"
#1045000
b110000011100010010100 (
1"
#1050000
0"
#1055000
b110001000001001100101 (
1"
#1060000
0"
#1065000
b110001100110000110110 (
1"
#1070000
0"
#1075000
b110010001011000000111 (
1"
#1080000
0"
#1085000
b110010101111111011000 (
1"
#1090000
0"
#1095000
b110011010100110101001 (
1"
#1100000
0"
#1105000
b110011111001101111010 (
1"
#1110000
0"
#1115000
b110100011110101001011 (
1"
#1120000
0"
#1125000
b110101000011100011100 (
1"
#1130000
0"
#1135000
b110101101000011101101 (
1"
#1140000
0"
#1145000
b110110001101010111110 (
1"
#1150000
0"
#1155000
b110110110010010001111 (
1"
#1160000
0"
#1165000
b110111010111001100000 (
1"
#1170000
0"
#1175000
b110111111100000110001 (
1"
#1180000
0"
#1185000
b111000100001000000010 (
1"
#1190000
0"
#1195000
b111001000101111010011 (
1"
#1200000
0"
#1205000
b111001101010110100100 (
1"
#1210000
0"
#1215000
b111010001111101110101 (
1"
#1220000
0"
#1225000
b111010110100101000110 (
1"
#1230000
0"
#1235000
b111011011001100010111 (
1"
#1240000
0"
#1245000
b111011111110011101000 (
1"
#1250000
0"
#1255000
b111100100011010111001 (
1"
#1260000
0"
#1265000
b111101001000010001010 (
1"
#1270000
0"
#1275000
b111101101101001011011 (
1"
#1280000
0"
#1285000
b111110010010000101100 (
1"
#1290000
0"
#1295000
b111110110110111111101 (
1"
#1300000
0"
#1305000
b111111011011111001110 (
1"
#1310000
0"
#1315000
b1000000000000110011111 (
1"
#1320000
0"
#1325000
b1000000100101101110000 (
1"
#1330000
0"
#1335000
b1000001001010101000001 (
1"
#1340000
0"
#1345000
b1000001101111100010010 (
1"
#1350000
0"
#1355000
b1000010010100011100011 (
1"
#1360000
0"
#1365000
b1000010111001010110100 (
1"
#1370000
0"
#1375000
b1000011011110010000101 (
1"
#1380000
0"
#1385000
b1000100000011001010110 (
1"
#1390000
0"
#1395000
b1000100101000000100111 (
1"
#1400000
0"
#1405000
b1000101001100111111000 (
1"
#1410000
0"
#1415000
b1000101110001111001001 (
1"
#1420000
0"
#1425000
b1000110010110110011010 (
1"
#1430000
0"
#1435000
b1000110111011101101011 (
1"
#1440000
0"
#1445000
b1000111100000100111100 (
1"
#1450000
0"
#1455000
b1001000000101100001101 (
1"
#1460000
0"
#1465000
b1001000101010011011110 (
1"
#1470000
0"
#1475000
b1001001001111010101111 (
1"
#1480000
0"
#1485000
b1001001110100010000000 (
1"
#1490000
0"
#1495000
b1001010011001001010001 (
1"
#1500000
0"
#1505000
b1001010111110000100010 (
1"
#1510000
0"
#1515000
b1001011100010111110011 (
1"
#1520000
0"
#1525000
b1001100000111111000100 (
1"
#1530000
0"
#1535000
b1001100101100110010101 (
1"
#1540000
0"
#1545000
b1001101010001101100110 (
1"
#1550000
0"
#1555000
b1001101110110100110111 (
1"
#1560000
0"
#1565000
b1001110011011100001000 (
1"
#1570000
0"
#1575000
b1001111000000011011001 (
1"
#1580000
0"
#1585000
b1001111100101010101010 (
1"
#1590000
0"
#1595000
b1010000001010001111011 (
1"
#1600000
0"
#1605000
b1010000101111001001100 (
1"
#1610000
0"
#1615000
b1010001010100000011101 (
1"
#1620000
0"
#1625000
b1010001111000111101110 (
1"
#1630000
0"
#1635000
b1010010011101110111111 (
1"
#1640000
0"
#1645000
b1010011000010110010000 (
1"
#1650000
0"
#1655000
b1010011100111101100001 (
1"
#1660000
0"
#1665000
b1010100001100100110010 (
1"
#1670000
0"
#1675000
b1010100110001100000011 (
1"
#1680000
0"
#1685000
b1010101010110011010100 (
1"
#1690000
0"
#1695000
b1010101111011010100101 (
1"
#1700000
0"
#1705000
b1010110100000001110110 (
1"
#1710000
0"
#1715000
b1010111000101001000111 (
1"
#1720000
0"
#1725000
b1010111101010000011000 (
1"
#1730000
0"
#1735000
b1011000001110111101001 (
1"
#1740000
0"
#1745000
b1011000110011110111010 (
1"
#1750000
0"
#1755000
b1011001011000110001011 (
1"
#1760000
0"
#1765000
b1011001111101101011100 (
1"
#1770000
0"
#1775000
b1011010100010100101101 (
1"
#1780000
0"
#1785000
b1011011000111011111110 (
1"
#1790000
0"
#1795000
b1011011101100011001111 (
1"
#1800000
0"
#1805000
b1011100010001010100000 (
1"
#1810000
0"
#1815000
b1011100110110001110001 (
1"
#1820000
0"
#1825000
b1011101011011001000010 (
1"
#1830000
0"
#1835000
b1011110000000000010011 (
1"
#1840000
0"
#1845000
b1011110100100111100100 (
1"
#1850000
0"
#1855000
b1011111001001110110101 (
1"
#1860000
0"
#1865000
b1011111101110110000110 (
1"
#1870000
0"
#1875000
b1100000010011101010111 (
1"
#1880000
0"
#1885000
b1100000111000100101000 (
1"
#1890000
0"
#1895000
b1100001011101011111001 (
1"
#1900000
0"
#1905000
b1100010000010011001010 (
1"
#1910000
0"
#1915000
b1100010100111010011011 (
1"
#1920000
0"
#1925000
b1100011001100001101100 (
1"
#1930000
0"
#1935000
b1100011110001000111101 (
1"
#1940000
0"
#1945000
b1100100010110000001110 (
1"
#1950000
0"
#1955000
b1100100111010111011111 (
1"
#1960000
0"
#1965000
b1100101011111110110000 (
1"
#1970000
0"
#1975000
b1100110000100110000001 (
1"
#1980000
0"
#1985000
b1100110101001101010010 (
1"
#1990000
0"
#1995000
b1100111001110100100011 (
1"
#2000000
0"
#2005000
b1100111110011011110100 (
1"
#2010000
0"
#2015000
b1101000011000011000101 (
1"
#2020000
0"
#2025000
b1101000111101010010110 (
1"
#2030000
0"
#2035000
b1101001100010001100111 (
1"
#2040000
0"
#2045000
b1101010000111000111000 (
1"
#2050000
0"
#2055000
b1101010101100000001001 (
1"
#2060000
0"
#2065000
b1101011010000111011010 (
1"
#2070000
0"
#2075000
b1101011110101110101011 (
1"
#2080000
0"
#2085000
b1101100011010101111100 (
1"
#2090000
0"
#2095000
b1101100111111101001101 (
1"
#2100000
0"
#2105000
b1101101100100100011110 (
1"
#2110000
0"
#2115000
b1101110001001011101111 (
1"
#2120000
0"
#2125000
b1101110101110011000000 (
1"
#2130000
0"
#2135000
b1101111010011010010001 (
1"
#2140000
0"
#2145000
b1101111111000001100010 (
1"
#2150000
0"
#2155000
b1110000011101000110011 (
1"
#2160000
0"
#2165000
b1110001000010000000100 (
1"
#2170000
0"
#2175000
b1110001100110111010101 (
1"
#2180000
0"
#2185000
b1110010001011110100110 (
1"
#2190000
0"
#2195000
b1110010110000101110111 (
1"
#2200000
0"
#2205000
b1110011010101101001000 (
1"
#2210000
0"
#2215000
b1110011111010100011001 (
1"
#2220000
0"
#2225000
b1110100011111011101010 (
1"
#2230000
0"
#2235000
b1110101000100010111011 (
1"
#2240000
0"
#2245000
b1110101101001010001100 (
1"
#2250000
0"
#2255000
b1110110001110001011101 (
1"
#2260000
0"
#2265000
b1110110110011000101110 (
1"
#2270000
0"
#2275000
b1110111010111111111111 (
1"
#2280000
0"
#2285000
b1110111111100111010000 (
1"
#2290000
0"
#2295000
b1111000100001110100001 (
1"
#2300000
0"
#2305000
b1111001000110101110010 (
1"
#2310000
0"
#2315000
b1111001101011101000011 (
1"
#2320000
0"
#2325000
b1111010010000100010100 (
1"
#2330000
0"
#2335000
b1111010110101011100101 (
1"
#2340000
0"
#2345000
b1111011011010010110110 (
1"
#2350000
0"
#2355000
b1111011111111010000111 (
1"
#2360000
0"
#2365000
b1111100100100001011000 (
1"
#2370000
0"
#2375000
b1111101001001000101001 (
1"
#2380000
0"
#2385000
b1111101101101111111010 (
1"
#2390000
0"
#2395000
b1111110010010111001011 (
1"
#2400000
0"
#2405000
b1111110110111110011100 (
1"
#2410000
0"
#2415000
b1111111011100101101101 (
1"
#2420000
0"
#2425000
b10000000000001100111110 (
1"
#2430000
0"
#2435000
b10000000100110100001111 (
1"
#2440000
0"
#2445000
b10000001001011011100000 (
1"
#2450000
0"
#2455000
b10000001110000010110001 (
1"
#2460000
0"
#2465000
b10000010010101010000010 (
1"
#2470000
0"
#2475000
b10000010111010001010011 (
1"
#2480000
0"
#2485000
b10000011011111000100100 (
1"
#2490000
0"
#2495000
b10000100000011111110101 (
1"
#2500000
0"
#2505000
b10000100101000111000110 (
1"
#2510000
0"
#2515000
b10000101001101110010111 (
1"
#2520000
0"
#2525000
b10000101110010101101000 (
1"
#2530000
0"
#2535000
b10000110010111100111001 (
1"
#2540000
0"
#2545000
b10000110111100100001010 (
1"
#2550000
0"
#2555000
b10000111100001011011011 (
1"
#2560000
0"
#2565000
b10001000000110010101100 (
1"
#2570000
0"
#2575000
b10001000101011001111101 (
1"
#2580000
0"
#2585000
b10001001010000001001110 (
1"
#2590000
0"
#2595000
b10001001110101000011111 (
1"
#2600000
0"
#2605000
b10001010011001111110000 (
1"
#2610000
0"
#2615000
b10001010111110111000001 (
1"
#2620000
0"
#2625000
b10001011100011110010010 (
1"
#2630000
0"
#2635000
b10001100001000101100011 (
1"
#2640000
0"
#2645000
b10001100101101100110100 (
1"
#2650000
0"
#2655000
b10001101010010100000101 (
1"
#2660000
0"
#2665000
b10001101110111011010110 (
1"
#2670000
0"
#2675000
b10001110011100010100111 (
1"
#2680000
0"
#2685000
b10001111000001001111000 (
1"
#2690000
0"
#2695000
b10001111100110001001001 (
1"
#2700000
0"
#2705000
b10010000001011000011010 (
1"
#2710000
0"
#2715000
b10010000101111111101011 (
1"
#2720000
0"
#2725000
b10010001010100110111100 (
1"
#2730000
0"
#2735000
b10010001111001110001101 (
1"
#2740000
0"
#2745000
b10010010011110101011110 (
1"
#2750000
0"
#2755000
b10010011000011100101111 (
1"
#2760000
0"
#2765000
b10010011101000100000000 (
1"
#2770000
0"
#2775000
b10010100001101011010001 (
1"
#2780000
0"
#2785000
b10010100110010010100010 (
1"
#2790000
0"
#2795000
b10010101010111001110011 (
1"
#2800000
0"
#2805000
b10010101111100001000100 (
1"
#2810000
0"
#2815000
b10010110100001000010101 (
1"
#2820000
0"
#2825000
b10010111000101111100110 (
1"
#2830000
0"
#2835000
b10010111101010110110111 (
1"
#2840000
0"
#2845000
b10011000001111110001000 (
1"
#2850000
0"
#2855000
b10011000110100101011001 (
1"
#2860000
0"
#2865000
b10011001011001100101010 (
1"
#2870000
0"
#2875000
b10011001111110011111011 (
1"
#2880000
0"
#2885000
b10011010100011011001100 (
1"
#2890000
0"
#2895000
b10011011001000010011101 (
1"
#2900000
0"
#2905000
b10011011101101001101110 (
1"
#2910000
0"
#2915000
b10011100010010000111111 (
1"
#2920000
0"
#2925000
b10011100110111000010000 (
1"
#2930000
0"
#2935000
b10011101011011111100001 (
1"
#2940000
0"
#2945000
b10011110000000110110010 (
1"
#2950000
0"
#2955000
b10011110100101110000011 (
1"
#2960000
0"
#2965000
b10011111001010101010100 (
1"
#2970000
0"
#2975000
b10011111101111100100101 (
1"
#2980000
0"
#2985000
b10100000010100011110110 (
1"
#2990000
0"
#2995000
b10100000111001011000111 (
1"
#3000000
0"
#3005000
b10100001011110010011000 (
1"
#3010000
0"
#3015000
b10100010000011001101001 (
1"
#3020000
0"
#3025000
b10100010101000000111010 (
1"
#3030000
0"
#3035000
b10100011001101000001011 (
1"
#3040000
0"
#3045000
b10100011110001111011100 (
1"
#3050000
0"
#3055000
b10100100010110110101101 (
1"
#3060000
0"
#3065000
b10100100111011101111110 (
1"
#3070000
0"
#3075000
b10100101100000101001111 (
1"
#3080000
0"
#3085000
b10100110000101100100000 (
1"
#3090000
0"
#3095000
b10100110101010011110001 (
1"
#3100000
0"
#3105000
b10100111001111011000010 (
1"
#3110000
0"
#3115000
b10100111110100010010011 (
1"
#3120000
0"
#3125000
b10101000011001001100100 (
1"
#3130000
0"
#3135000
b10101000111110000110101 (
1"
#3140000
0"
#3145000
b10101001100011000000110 (
1"
#3150000
0"
#3155000
b10101010000111111010111 (
1"
#3160000
0"
#3165000
b10101010101100110101000 (
1"
#3170000
0"
#3175000
b10101011010001101111001 (
1"
#3180000
0"
#3185000
b10101011110110101001010 (
1"
#3190000
0"
#3195000
b10101100011011100011011 (
1"
#3200000
0"
#3205000
b10101101000000011101100 (
1"
#3210000
0"
#3215000
b10101101100101010111101 (
1"
#3220000
0"
#3225000
b10101110001010010001110 (
1"
#3230000
0"
#3235000
b10101110101111001011111 (
1"
#3240000
0"
#3245000
b10101111010100000110000 (
1"
#3250000
0"
#3255000
b10101111111001000000001 (
1"
#3260000
0"
#3265000
b10110000011101111010010 (
1"
#3270000
0"
#3275000
b10110001000010110100011 (
1"
#3280000
0"
#3285000
b10110001100111101110100 (
1"
#3290000
0"
#3295000
b10110010001100101000101 (
1"
#3300000
0"
#3305000
b10110010110001100010110 (
1"
#3310000
0"
#3315000
b10110011010110011100111 (
1"
#3320000
0"
#3325000
b10110011111011010111000 (
1"
#3330000
0"
#3335000
b10110100100000010001001 (
1"
#3340000
0"
#3345000
b10110101000101001011010 (
1"
#3350000
0"
#3355000
b10110101101010000101011 (
1"
#3360000
0"
#3365000
b10110110001110111111100 (
1"
#3370000
0"
#3375000
b10110110110011111001101 (
1"
#3380000
0"
#3385000
b10110111011000110011110 (
1"
#3390000
0"
#3395000
b10110111111101101101111 (
1"
#3400000
0"
#3405000
b10111000100010101000000 (
1"
#3410000
0"
#3415000
b10111001000111100010001 (
1"
#3420000
0"
#3425000
b10111001101100011100010 (
1"
#3430000
0"
#3435000
b10111010010001010110011 (
1"
#3440000
0"
#3445000
b10111010110110010000100 (
1"
#3450000
0"
#3455000
b10111011011011001010101 (
1"
#3460000
0"
#3465000
b10111100000000000100110 (
1"
#3470000
0"
#3475000
b10111100100100111110111 (
1"
#3480000
0"
#3485000
b10111101001001111001000 (
1"
#3490000
0"
#3495000
b10111101101110110011001 (
1"
#3500000
0"
#3505000
b10111110010011101101010 (
1"
#3510000
0"
#3515000
b10111110111000100111011 (
1"
#3520000
0"
#3525000
b10111111011101100001100 (
1"
#3530000
0"
#3535000
b11000000000010011011101 (
1"
#3540000
0"
#3545000
b11000000100111010101110 (
1"
#3550000
0"
#3555000
b11000001001100001111111 (
1"
#3560000
0"
#3565000
b11000001110001001010000 (
1"
#3570000
0"
#3575000
b11000010010110000100001 (
1"
#3580000
0"
#3585000
b11000010111010111110010 (
1"
#3590000
0"
#3595000
b11000011011111111000011 (
1"
#3600000
0"
#3605000
b11000100000100110010100 (
1"
#3610000
0"
#3615000
b11000100101001101100101 (
1"
#3620000
0"
#3625000
b11000101001110100110110 (
1"
#3630000
0"
#3635000
b11000101110011100000111 (
1"
#3640000
0"
#3645000
b11000110011000011011000 (
1"
#3650000
0"
#3655000
b11000110111101010101001 (
1"
#3660000
0"
#3665000
b11000111100010001111010 (
1"
#3670000
0"
#3675000
b11001000000111001001011 (
1"
#3680000
0"
#3685000
b11001000101100000011100 (
1"
#3690000
0"
#3695000
b11001001010000111101101 (
1"
#3700000
0"
#3705000
b11001001110101110111110 (
1"
#3710000
0"
#3715000
b11001010011010110001111 (
1"
#3720000
0"
#3725000
b11001010111111101100000 (
1"
#3730000
0"
#3735000
b11001011100100100110001 (
1"
#3740000
0"
#3745000
b11001100001001100000010 (
1"
#3750000
0"
#3755000
b11001100101110011010011 (
1"
#3760000
0"
#3765000
b11001101010011010100100 (
1"
#3770000
0"
#3775000
b11001101111000001110101 (
1"
#3780000
0"
#3785000
b11001110011101001000110 (
1"
#3790000
0"
#3795000
b11001111000010000010111 (
1"
#3800000
0"
#3805000
b11001111100110111101000 (
1"
#3810000
0"
#3815000
b11010000001011110111001 (
1"
#3820000
0"
#3825000
b11010000110000110001010 (
1"
#3830000
0"
#3835000
b11010001010101101011011 (
1"
#3840000
0"
#3845000
b11010001111010100101100 (
1"
#3850000
0"
#3855000
b11010010011111011111101 (
1"
#3860000
0"
#3865000
b11010011000100011001110 (
1"
#3870000
0"
#3875000
b11010011101001010011111 (
1"
#3880000
0"
#3885000
b11010100001110001110000 (
1"
#3890000
0"
#3895000
b11010100110011001000001 (
1"
#3900000
0"
#3905000
b11010101011000000010010 (
1"
#3910000
0"
#3915000
b11010101111100111100011 (
1"
#3920000
0"
#3925000
b11010110100001110110100 (
1"
#3930000
0"
#3935000
b11010111000110110000101 (
1"
#3940000
0"
#3945000
b11010111101011101010110 (
1"
#3950000
0"
#3955000
b11011000010000100100111 (
1"
#3960000
0"
#3965000
b11011000110101011111000 (
1"
#3970000
0"
#3975000
b11011001011010011001001 (
1"
#3980000
0"
#3985000
b11011001111111010011010 (
1"
#3990000
0"
#3995000
b11011010100100001101011 (
1"
#4000000
0"
#4005000
b11011011001001000111100 (
1"
#4010000
0"
#4015000
b11011011101110000001101 (
1"
#4020000
0"
#4025000
b11011100010010111011110 (
1"
#4030000
0"
#4035000
b11011100110111110101111 (
1"
#4040000
0"
#4045000
b11011101011100110000000 (
1"
#4050000
0"
#4055000
b11011110000001101010001 (
1"
#4060000
0"
#4065000
b11011110100110100100010 (
1"
#4070000
0"
#4075000
b11011111001011011110011 (
1"
#4080000
0"
#4085000
b11011111110000011000100 (
1"
#4090000
0"
#4095000
b11100000010101010010101 (
1"
#4100000
0"
#4105000
b11100000111010001100110 (
1"
#4110000
0"
#4115000
b11100001011111000110111 (
1"
#4120000
0"
#4125000
b11100010000100000001000 (
1"
#4130000
0"
#4135000
b11100010101000111011001 (
1"
#4140000
0"
#4145000
b11100011001101110101010 (
1"
#4150000
0"
#4155000
b11100011110010101111011 (
1"
#4160000
0"
#4165000
b11100100010111101001100 (
1"
#4170000
0"
#4175000
b11100100111100100011101 (
1"
#4180000
0"
#4185000
b11100101100001011101110 (
1"
#4190000
0"
#4195000
b11100110000110010111111 (
1"
#4200000
0"
#4205000
b11100110101011010010000 (
1"
#4210000
0"
#4215000
b11100111010000001100001 (
1"
#4220000
0"
#4225000
b11100111110101000110010 (
1"
#4230000
0"
#4235000
b11101000011010000000011 (
1"
#4240000
0"
#4245000
b11101000111110111010100 (
1"
#4250000
0"
#4255000
b11101001100011110100101 (
1"
#4260000
0"
#4265000
b11101010001000101110110 (
1"
#4270000
0"
#4275000
b11101010101101101000111 (
1"
#4280000
0"
#4285000
b11101011010010100011000 (
1"
#4290000
0"
#4295000
b11101011110111011101001 (
1"
#4300000
0"
#4305000
b11101100011100010111010 (
1"
#4310000
0"
#4315000
b11101101000001010001011 (
1"
#4320000
0"
#4325000
b11101101100110001011100 (
1"
#4330000
0"
#4335000
b11101110001011000101101 (
1"
#4340000
0"
#4345000
b11101110101111111111110 (
1"
#4350000
0"
#4355000
b11101111010100111001111 (
1"
#4360000
0"
#4365000
b11101111111001110100000 (
1"
#4370000
0"
#4375000
b11110000011110101110001 (
1"
#4380000
0"
#4385000
b11110001000011101000010 (
1"
#4390000
0"
#4395000
b11110001101000100010011 (
1"
#4400000
0"
#4405000
b11110010001101011100100 (
1"
#4410000
0"
#4415000
b11110010110010010110101 (
1"
#4420000
0"
#4425000
b11110011010111010000110 (
1"
#4430000
0"
#4435000
b11110011111100001010111 (
1"
#4440000
0"
#4445000
b11110100100001000101000 (
1"
#4450000
0"
#4455000
b11110101000101111111001 (
1"
#4460000
0"
#4465000
b11110101101010111001010 (
1"
#4470000
0"
#4475000
b11110110001111110011011 (
1"
#4480000
0"
#4485000
b11110110110100101101100 (
1"
#4490000
0"
#4495000
b11110111011001100111101 (
1"
#4500000
0"
#4505000
b11110111111110100001110 (
1"
#4510000
0"
