final_project_1_3/final_project_1_3.srcs/sources_1/new/sqr_wav_gen.v
    `timescale 1ns / 1ps
    //////////////////////////////////////////////////////////////////////////////////
    // Company: 
    // Engineer: 
    // 
    // Create Date: 09/26/2024 07:36:44 PM
    // Design Name: 
    // Module Name: sqr_wav_gen
    // Project Name: 
    // Target Devices: 
    // Tool Versions: 
    // Description: 
    // 
    // Dependencies: 
    // 
    // Revision:
    // Revision 0.01 - File Created
    // Additional Comments:
    // 
    //////////////////////////////////////////////////////////////////////////////////
    
    
    module sqr_wav_gen(
        input wire clk,
        input wire reset,
        input wire [31:0] freq,
        output reg [7:0] wav_out
    );
    
    reg [31:0] counter;
    reg [31:0] max;
    
    always @(posedge clk) begin
        if (reset) begin
            counter <= 0;
            wav_out <= 8'h00;
        end else begin
            if (counter >= max) begin
                counter <= 0;
                wav_out <= ~wav_out;  // Toggle output after max period
            end else begin
                counter <= counter + 1;
            end
        end
    end
    
    // Combinational block to calculate max value
    always @(*) begin
        if (freq == 0) begin
            max = 32'd50000000; // Large number to generate very low frequency
        end else begin
            max = 50000000 / freq;
        end
    end
endmodule

final_project_1_3/final_project_1_3.srcs/sim_1/new/sqr_wav_gen_tb.v
`timescale 1ns / 1ps
//////////////////////////////////////////////////////////////////////////////////
// Company: 
// Engineer: 
// 
// Create Date: 09/27/2024 11:46:18 AM
// Design Name: 
// Module Name: sqr_wav_gen_tb
// Project Name: 
// Target Devices: 
// Tool Versions: 
// Description: 
// 
// Dependencies: 
// 
// Revision:
// Revision 0.01 - File Created
// Additional Comments:
// 
//////////////////////////////////////////////////////////////////////////////////

module sqr_wav_gen_tb;

    // Testbench Signals
    reg clk;
    reg reset;
    reg [31:0] freq;   // Input frequency
    wire [7:0] wav_out; // Output waveform

    // Instantiate the sqr_wav_gen module
    sqr_wav_gen uut (
        .clk(clk),
        .reset(reset),
        .freq(freq),
        .wav_out(wav_out)
    );

    // Clock generation: 50 MHz clock (period = 20ns)
    initial begin
        clk = 0;
        forever #10 clk = ~clk; // Toggle clock every 10ns -> 50 MHz
    end

    // Test sequence
    initial begin
        // Initialize signals
        reset = 1;         // Assert reset
        freq = 32'h0;      // Initial frequency set to 0
        
        // Wait for some time to ensure reset takes effect
        #100;
        reset = 0;         // De-assert reset

        // Apply different frequencies and observe waveform output
        // Test with various frequencies based on MIDI notes (same as before)
        
        // MIDI Note 60 (Middle C) - ~261.63 Hz
        freq = 32'd192576; // 50M / 261.63 -> 192576
        #50000;            // Wait to observe the output for some time
        
        // MIDI Note 64 (E4) - ~329.63 Hz
        freq = 32'd151685; // 50M / 329.63 -> 151685
        #50000;            // Wait to observe the output

        // MIDI Note 67 (G4) - ~392.00 Hz
        freq = 32'd127882; // 50M / 392.00 -> 127882
        #50000;            // Wait to observe the output
        
        // MIDI Note 72 (C5) - ~523.25 Hz
        freq = 32'd95655;  // 50M / 523.25 -> 95655
        #50000;            // Wait to observe the output
        
        // MIDI Note 76 (E5) - ~659.25 Hz
        freq = 32'd75853;  // 50M / 659.25 -> 75853
        #50000;            // Wait to observe the output

        // MIDI Note 79 (G5) - ~783.99 Hz
        freq = 32'd63969;  // 50M / 783.99 -> 63969
        #50000;            // Wait to observe the output

        // Finish the simulation
        $finish;
    end

endmodule

final_project_1_3/final_project_1_3.sim/sim_1/behav/xsim/sqr_wav_gen_tb.vcd
$date
   Wed Oct  2 00:13:50 2024
$end

$version
  2023.2
  $dumpfile ("sqr_wav_gen_tb.vcd") 
$end

$timescale
  1ps
$end

$scope module sqr_wav_gen_tb $end
$var reg 1 ! clk $end
$var reg 1 " reset $end
$var reg 32 # freq [31:0] $end
$var wire 8 $ wav_out [7:0] $end
$scope module uut $end
$var wire 1 % clk $end
$var wire 1 & reset $end
$var wire 32 ' freq [31:0] $end
$var reg 8 ( wav_out [7:0] $end
$var reg 32 ) counter [31:0] $end
$var reg 32 * max [31:0] $end
$upscope $end
$upscope $end
$enddefinitions $end

#0
$dumpvars
0!
1"
b0 #
bx $
0%
1&
b0 '
bx (
bx )
b11111111111111111111111111111111 *
$end

#5000
1!
b0 $
1%
b0 (
b0 )

#10000
0!
0"
0%
0&

#15000
1!
b11111111 $
1%
b11111111 (
b1 )

#20000
0!
b101111000001000000 #
0%
b101111000001000000 '
b100000011 *

#25000
1!
1%
b10 )

#30000
0!
0%

#35000
1!
1%
b11 )

#40000
0!
0%

#45000
1!
1%
b100 )

#50000
0!
0%

#55000
1!
1%
b101 )

#60000
0!
0%

#65000
1!
1%
b110 )

#70000
0!
0%

#75000
1!
1%
b111 )

#80000
0!
0%

#85000
1!
1%
b1000 )

#90000
0!
0%

#95000
1!
1%
b1001 )

#100000
0!
0%

#105000
1!
1%
b1010 )

#110000
0!
0%

#115000
1!
1%
b1011 )

#120000
0!
0%

#125000
1!
1%
b1100 )

#130000
0!
0%

#135000
1!
1%
b1101 )

#140000
0!
0%

#145000
1!
1%
b1110 )

#150000
0!
0%

#155000
1!
1%
b1111 )

#160000
0!
0%

#165000
1!
1%
b10000 )

#170000
0!
0%

#175000
1!
1%
b10001 )

#180000
0!
0%

#185000
1!
1%
b10010 )

#190000
0!
0%

#195000
1!
1%
b10011 )

#200000
0!
0%

#205000
1!
1%
b10100 )

#210000
0!
0%

#215000
1!
1%
b10101 )

#220000
0!
0%

#225000
1!
1%
b10110 )

#230000
0!
0%

#235000
1!
1%
b10111 )

#240000
0!
0%

#245000
1!
1%
b11000 )

#250000
0!
0%

#255000
1!
1%
b11001 )

#260000
0!
0%

#265000
1!
1%
b11010 )

#270000
0!
0%

#275000
1!
1%
b11011 )

#280000
0!
0%

#285000
1!
1%
b11100 )

#290000
0!
0%

#295000
1!
1%
b11101 )

#300000
0!
0%

#305000
1!
1%
b11110 )

#310000
0!
0%

#315000
1!
1%
b11111 )

#320000
0!
0%

#325000
1!
1%
b100000 )

#330000
0!
0%

#335000
1!
1%
b100001 )

#340000
0!
0%

#345000
1!
1%
b100010 )

#350000
0!
0%

#355000
1!
1%
b100011 )

#360000
0!
0%

#365000
1!
1%
b100100 )

#370000
0!
0%

#375000
1!
1%
b100101 )

#380000
0!
0%

#385000
1!
1%
b100110 )

#390000
0!
0%

#395000
1!
1%
b100111 )

#400000
0!
0%

#405000
1!
1%
b101000 )

#410000
0!
0%

#415000
1!
1%
b101001 )

#420000
0!
0%

#425000
1!
1%
b101010 )

#430000
0!
0%

#435000
1!
1%
b101011 )

#440000
0!
0%

#445000
1!
1%
b101100 )

#450000
0!
0%

#455000
1!
1%
b101101 )

#460000
0!
0%

#465000
1!
1%
b101110 )

#470000
0!
0%

#475000
1!
1%
b101111 )

#480000
0!
0%

#485000
1!
1%
b110000 )

#490000
0!
0%

#495000
1!
1%
b110001 )

#500000
0!
0%

#505000
1!
1%
b110010 )

#510000
0!
0%

#515000
1!
1%
b110011 )

#520000
0!
0%

#525000
1!
1%
b110100 )

#530000
0!
0%

#535000
1!
1%
b110101 )

#540000
0!
0%

#545000
1!
1%
b110110 )

#550000
0!
0%

#555000
1!
1%
b110111 )

#560000
0!
0%

#565000
1!
1%
b111000 )

#570000
0!
0%

#575000
1!
1%
b111001 )

#580000
0!
0%

#585000
1!
1%
b111010 )

#590000
0!
0%

#595000
1!
1%
b111011 )

#600000
0!
0%

#605000
1!
1%
b111100 )

#610000
0!
0%

#615000
1!
1%
b111101 )

#620000
0!
0%

#625000
1!
1%
b111110 )

#630000
0!
0%

#635000
1!
1%
b111111 )

#640000
0!
0%

#645000
1!
1%
b1000000 )

#650000
0!
0%

#655000
1!
1%
b1000001 )

#660000
0!
0%

#665000
1!
1%
b1000010 )

#670000
0!
0%

#675000
1!
1%
b1000011 )

#680000
0!
0%

#685000
1!
1%
b1000100 )

#690000
0!
0%

#695000
1!
1%
b1000101 )

#700000
0!
0%

#705000
1!
1%
b1000110 )

#710000
0!
0%

#715000
1!
1%
b1000111 )

#720000
0!
0%

#725000
1!
1%
b1001000 )

#730000
0!
0%

#735000
1!
1%
b1001001 )

#740000
0!
0%

#745000
1!
1%
b1001010 )

#750000
0!
0%

#755000
1!
1%
b1001011 )

#760000
0!
0%

#765000
1!
1%
b1001100 )

#770000
0!
0%

#775000
1!
1%
b1001101 )

#780000
0!
0%

#785000
1!
1%
b1001110 )

#790000
0!
0%

#795000
1!
1%
b1001111 )

#800000
0!
0%

#805000
1!
1%
b1010000 )

#810000
0!
0%

#815000
1!
1%
b1010001 )

#820000
0!
0%

#825000
1!
1%
b1010010 )

#830000
0!
0%

#835000
1!
1%
b1010011 )

#840000
0!
0%

#845000
1!
1%
b1010100 )

#850000
0!
0%

#855000
1!
1%
b1010101 )

#860000
0!
0%

#865000
1!
1%
b1010110 )

#870000
0!
0%

#875000
1!
1%
b1010111 )

#880000
0!
0%

#885000
1!
1%
b1011000 )

#890000
0!
0%

#895000
1!
1%
b1011001 )

#900000
0!
0%

#905000
1!
1%
b1011010 )

#910000
0!
0%

#915000
1!
1%
b1011011 )

#920000
0!
0%

#925000
1!
1%
b1011100 )

#930000
0!
0%

#935000
1!
1%
b1011101 )

#940000
0!
0%

#945000
1!
1%
b1011110 )

#950000
0!
0%

#955000
1!
1%
b1011111 )

#960000
0!
0%

#965000
1!
1%
b1100000 )

#970000
0!
0%

#975000
1!
1%
b1100001 )

#980000
0!
0%

#985000
1!
1%
b1100010 )

#990000
0!
0%

#995000
1!
1%
b1100011 )

